tied_autoencoder_keras/__init__.py
tied_autoencoder_keras/autoencoders.py
tied_autoencoder_keras-0.4.0.dist-info/METADATA
tied_autoencoder_keras-0.4.0.dist-info/RECORD
tied_autoencoder_keras-0.4.0.dist-info/WHEEL
tied_autoencoder_keras-0.4.0.dist-info/top_level.txt
